qranalyze/__init__.py
qranalyze/core.py
qranalyze-0.1.0.dist-info/licenses/LICENSE
qranalyze-0.1.0.dist-info/METADATA
qranalyze-0.1.0.dist-info/WHEEL
qranalyze-0.1.0.dist-info/top_level.txt
qranalyze-0.1.0.dist-info/RECORD
