Metadata-Version: 2.4
Name: qranalyze
Version: 0.1.0
Summary: A QR code analysis and utility package
Author-email: Bradley Neild <bradleyneild@tfss.dev>
License: MIT
Project-URL: Homepage, https://github.com/BradleyNeild/qranalyze
Project-URL: Bug Tracker, https://github.com/BradleyNeild/qranalyze/issues
Keywords: qr,qrcode,analysis,utility
Classifier: Development Status :: 3 - Alpha
Classifier: Intended Audience :: Developers
Classifier: License :: OSI Approved :: MIT License
Classifier: Operating System :: OS Independent
Classifier: Programming Language :: Python :: 3
Classifier: Programming Language :: Python :: 3.7
Classifier: Programming Language :: Python :: 3.8
Classifier: Programming Language :: Python :: 3.9
Classifier: Programming Language :: Python :: 3.10
Classifier: Programming Language :: Python :: 3.11
Classifier: Programming Language :: Python :: 3.12
Requires-Python: >=3.7
License-File: LICENSE
Dynamic: license-file
